libadalina/__init__.py
libadalina/__main__.py
libadalina/exceptions/input_file_exception.py
libadalina/graph/__init__.py
libadalina/graph/constants.py
libadalina/graph/coordinate_formats.py
libadalina/graph/graph_factory.py
libadalina/readers/__init__.py
libadalina/readers/open_street_map.py
libadalina/readers/reader.py
libadalina/sedona_integration/__init__.py
libadalina/sedona_integration/sedona_configuration.py
libadalina/utils/__init__.py
libadalina/utils/networkx_utils.py
libadalina/utils/spark_utils.py
libadalina/utils/timing.py
libadalina/writers/to_csv.py
libadalina/writers/to_geopackage.py
libadalina/writers/to_shapefile.py
libadalina-0.1.0.dist-info/licenses/LICENSE
libadalina-0.1.0.dist-info/METADATA
libadalina-0.1.0.dist-info/WHEEL
libadalina-0.1.0.dist-info/entry_points.txt
libadalina-0.1.0.dist-info/top_level.txt
libadalina-0.1.0.dist-info/RECORD
