Metadata-Version: 2.4
Name: libadalina
Version: 0.1.0
Summary: A library for graph analytics with geographic data
Author-email: Marco Casazza <d.marcocasazza@gmail.com>, Alberto Ceselli <alberto.ceselli@unimi.it>, Marco Premoli <marco.premoli@unimi.it>
License-Expression: MIT
Project-URL: Homepage, https://gitlab.com/amelia_unimi/libadalina
Classifier: Development Status :: 3 - Alpha
Classifier: Intended Audience :: Developers
Classifier: Programming Language :: Python :: 3
Classifier: Programming Language :: Python :: 3.10
Requires-Python: ~=3.10
License-File: LICENSE
Requires-Dist: apache-sedona[spark]==1.7.1
Requires-Dist: pyspark==3.3.2
Requires-Dist: pandas==2.2.3
Requires-Dist: geopandas==1.0.1
Requires-Dist: networkx==3.4.2
Requires-Dist: shapely==2.1.1
Requires-Dist: matplotlib==3.10.3
Requires-Dist: click==8.2.1
Requires-Dist: install-jdk==1.1.0
Provides-Extra: dev
Requires-Dist: pytest==8.4.1; extra == "dev"
Requires-Dist: black; extra == "dev"
Requires-Dist: isort; extra == "dev"
Dynamic: license-file
